README.txt
plac_ini.py
setup.py
plac_ini.egg-info/PKG-INFO
plac_ini.egg-info/SOURCES.txt
plac_ini.egg-info/dependency_links.txt
plac_ini.egg-info/not-zip-safe
plac_ini.egg-info/requires.txt
plac_ini.egg-info/top_level.txt