Metadata-Version: 1.1
Name: plac-ini
Version: 0.9.4
Summary: Adds configuration file support to plac
Home-page: https://github.com/fprimex/plac_ini
Author: Brent Woodruff
Author-email: brent@fprimex.com
License: BSD License
Keywords: command line arguments ini file parser
Platform: All
Classifier: Development Status :: 3 - Alpha
Classifier: Intended Audience :: Developers
Classifier: License :: OSI Approved :: BSD License
Classifier: Natural Language :: English
Classifier: Operating System :: OS Independent
Classifier: Programming Language :: Python
Classifier: Programming Language :: Python :: 3
Classifier: Topic :: Software Development :: Libraries
Classifier: Topic :: Utilities
